awkward_cpp/__init__.py
awkward_cpp/_kernel_signatures.py
awkward_cpp/cpu_kernels.py
awkward_cpp/libawkward.py
awkward_cpp/lib/_ext.cpython-314-aarch64-linux-musl.so
awkward_cpp/lib/libawkward-cpu-kernels.so
awkward_cpp/lib/libawkward.so
awkward_cpp.libs/libgcc_s-2d945d6c.so.1
awkward_cpp.libs/libstdc++-85f2cd6d.so.6.0.33
awkward_cpp-49.dist-info/METADATA
awkward_cpp-49.dist-info/WHEEL
awkward_cpp-49.dist-info/RECORD
awkward_cpp-49.dist-info/licenses/LICENSE
awkward_cpp-49.dist-info/licenses/rapidjson/license.txt
